marshmallow/__init__.py
marshmallow/base.py
marshmallow/class_registry.py
marshmallow/compat.py
marshmallow/decorators.py
marshmallow/exceptions.py
marshmallow/fields.py
marshmallow/marshalling.py
marshmallow/ordereddict.py
marshmallow/orderedset.py
marshmallow/schema.py
marshmallow/utils.py
marshmallow/validate.py
marshmallow/warnings.py
marshmallow2-2.20.2.dist-info/DESCRIPTION.rst
marshmallow2-2.20.2.dist-info/METADATA
marshmallow2-2.20.2.dist-info/RECORD
marshmallow2-2.20.2.dist-info/WHEEL
marshmallow2-2.20.2.dist-info/metadata.json
marshmallow2-2.20.2.dist-info/top_level.txt
