Metadata-Version: 2.0
Name: marshmallow2
Version: 2.20.2
Summary: A lightweight library for converting complex datatypes to and from native Python datatypes.
Home-page: https://github.com/marshmallow-code/marshmallow
Author: Steven Loria
Author-email: sloria1@gmail.com
License: MIT
Keywords: serialization,rest,json,api,marshal,marshalling,deserialization,validation,schema
Platform: UNKNOWN
Classifier: Development Status :: 5 - Production/Stable
Classifier: Intended Audience :: Developers
Classifier: License :: OSI Approved :: MIT License
Classifier: Programming Language :: Python :: 2
Classifier: Programming Language :: Python :: 2.7
Classifier: Programming Language :: Python :: 3
Classifier: Programming Language :: Python :: 3.4
Classifier: Programming Language :: Python :: 3.5
Classifier: Programming Language :: Python :: 3.6
Classifier: Programming Language :: Python :: 3.7
Provides-Extra: dev
Requires-Dist: flake8 (==3.7.4); extra == 'dev'
Requires-Dist: pytest; extra == 'dev'
Requires-Dist: python-dateutil; extra == 'dev'
Requires-Dist: pytz; extra == 'dev'
Requires-Dist: simplejson; extra == 'dev'
Requires-Dist: tox; extra == 'dev'
Provides-Extra: docs
Requires-Dist: alabaster (==0.7.12); extra == 'docs'
Requires-Dist: sphinx (==2.1.2); extra == 'docs'
Requires-Dist: sphinx-issues (==1.2.0); extra == 'docs'
Requires-Dist: sphinx-version-warning (==1.1.2); extra == 'docs'
Provides-Extra: lint
Requires-Dist: flake8 (==3.7.4); extra == 'lint'
Provides-Extra: reco
Requires-Dist: python-dateutil; extra == 'reco'
Requires-Dist: simplejson; extra == 'reco'
Provides-Extra: tests
Requires-Dist: pytest; extra == 'tests'
Requires-Dist: pytz; extra == 'tests'
